ssmtoybox/__init__.py
ssmtoybox/mtran.py
ssmtoybox/ssinf.py
ssmtoybox/ssmod.py
ssmtoybox/utils.py
ssmtoybox/bq/__init__.py
ssmtoybox/bq/bqkern.py
ssmtoybox/bq/bqmod.py
ssmtoybox/bq/bqmtran.py
ssmtoybox/tests/__init__.py
ssmtoybox/tests/test_bqkern.py
ssmtoybox/tests/test_bqmod.py
ssmtoybox/tests/test_bqmtran.py
ssmtoybox/tests/test_mtran.py
ssmtoybox/tests/test_ssinf.py
ssmtoybox/tests/test_ssmod.py
ssmtoybox/tests/test_utils.py
ssmtoybox-0.1.1a0.dist-info/LICENSE
ssmtoybox-0.1.1a0.dist-info/METADATA
ssmtoybox-0.1.1a0.dist-info/WHEEL
ssmtoybox-0.1.1a0.dist-info/top_level.txt
ssmtoybox-0.1.1a0.dist-info/RECORD
