Metadata-Version: 2.1
Name: ssmtoybox
Version: 0.1.1a0
Summary: Local filters based on Bayesian quadrature
Home-page: https://github.com/jacobnzw/SSMToybox/tree/v0.1.1-alpha
Author: Jakub Prüher
Author-email: jacobnzw@gmail.com
License: MIT
Platform: UNKNOWN
Classifier: Programming Language :: Python :: 3
Classifier: License :: OSI Approved :: MIT License
Classifier: Operating System :: OS Independent
Classifier: Development Status :: 3 - Alpha
Classifier: Intended Audience :: Education
Classifier: Intended Audience :: Science/Research
